{
  "@context": "http://www.w3.org/ns/anno.jsonld",
  "id": "http://visual-essays.app/annotations/?include=description&target=pelargonium/f82cac90",
  "type": "AnnotationPage",
  "partOf": {
    "id": "http://visual-essays.app/annotations/?include=description&target=pelargonium/f82cac90",
    "total": 1,
    "modified": "2021-03-02T14:40:26.388248"
  },
  "startIndex": 0,
  "items": [
    {
      "type": "Annotation",
      "body": [
        {
          "type": "TextualBody",
          "value": "Harvesting pelargonium",
          "purpose": "commenting"
        }
      ],
      "target": {
        "selector": {
          "type": "FragmentSelector",
          "conformsTo": "http://www.w3.org/TR/media-frags/",
          "value": "xywh=pixel:1258.481201171875,53.869873046875,1297.630126953125,879.3464965820312"
        },
        "id": "pelargonium/f82cac90"
      },
      "@context": "http://www.w3.org/ns/anno.jsonld",
      "id": "pelargonium/f82cac90/42dae574",
      "seq": 0
    }
  ]
}