{
  "type": "FeatureCollection",
  "features": [
    {
      "type": "Feature",
      "properties": {},
      "geometry": {
        "type": "Polygon",
        "coordinates": [
          [
            [
              -77.06294417381287,
              38.91473858696758
            ],
            [
              -77.06298038363457,
              38.914709369277276
            ],
            [
              -77.06296294927597,
              38.914434931099215
            ],
            [
              -77.06292137503624,
              38.91440884376469
            ],
            [
              -77.06278324127197,
              38.914411974245354
            ],
            [
              -77.06275105476378,
              38.91443910507186
            ],
            [
              -77.06276714801788,
              38.91471354323379
            ],
            [
              -77.06281408667564,
              38.91474276092236
            ],
            [
              -77.06294417381287,
              38.91473858696758
            ]
          ]
        ]
      }
    }
  ]
}
